Workbook

Sheet Como ler
A1: De-para entre a taxonomia de temas e o risk tracking corporativo
A3: O que este arquivo responde
A4: Dado um fato de mídia já classificado na taxonomia de três níveis, qual risco corporativo da Aegea ele materializa. A ligação é feita no nível do subtema, que é o nível em que a notícia é classificada.
A6: Fontes e datas de corte
A7: Taxonomia de temas: versão de três níveis fechada em 07/10/2026. 104 subtemas, 7 pilares.
A8: Risk tracking: 32 riscos em 8 clusters, com severidade validada pela Aegea em 07/10/2026. Severidade reproduzida como recebida, sem recálculo.
A9: Atribuição subtema para risco: premissa Peers, data de corte 08/10/2026. Não validada com a área de Riscos da Aegea. É isto que esta reunião precisa decidir.
A11: Regra de atribuição usada
A12: Cada subtema recebe um risco primário, que é o risco onde o dano se materializa, e não o risco de onde vem a narrativa. Exemplo: reajuste tarifário gera reação da comunidade, mas o dano se materializa no eixo Legal e Regulatório, porque o ato é regulatório e é lá que a empresa responde.
A13: O risco secundário registra a segunda leitura legítima do mesmo fato. Serve para discussão, não para contagem. Somar primário e secundário gera dupla contagem.
A14: Quatro subtemas ficam como Sem enquadramento. São narrativa institucional ou impacto positivo, sem risco corporativo correspondente. A ausência é deliberada, não é falha de mapeamento.
A16: Coluna de exemplo de notícia
... A29: Amarelo: preenchimento da Aegea na validação. Verde: exemplo com lastro na base de janeiro. Cinza: subtema sem enquadramento de risco.

Sheet Visão Fernanda
A1: Nível 1: Pilar reputacional | B1: Nível 2: Tema estratégico | C1: Nível 3: Subtema | D1: LSO | E1: Formato | F1: Detalhamento | G1: Pauta | H1: Campo de classificação da empresa | I1: To do Comunicação
A2: 1. Governança | B2: Governança corporativa | C2: Estrutura de governança / Conselho e comitês | D2: Credibilidade | E2: Notícias/Publicações | G2: Espontânea | H2: Concorrentes | I2: Definição de porta-vozes
A3: 1. Governança | B3: Governança corporativa | C3: Acionistas | D3: Credibilidade | E3: Comunicados | G3: Produzida | H3: Unidades Aegea | I3: Preenchimento planilha
A4: 1. Governança | B4: Contratos e Regulação | C4: Cumprimento contratual | D4: Legitimidade | E4: Entrevistas | G4: Provocada | I4: Validar taxonomia
A5: 1. Governança | B5: Contratos e Regulação | C5: Revisão e renovação de contratos | D5: Legitimidade | E5: Nota explicativa | G5: Publicidade | I5: Usuários
A6: 1. Governança | B6: Contratos e Regulação | C6: Reequilíbrio econômico-financeiro | D6: Legitimidade | I6: Reprisk
A7: 1. Governança | B7: Contratos e Regulação | C7: Segurança jurídica | D7: Legitimidade | I7: Porta vozes
A8: 1. Governança | B8: Contratos e Regulação | C8: Fiscalização regulatória | D8: Legitimidade
A9: 1. Governança | B9: Contratos e Regulação | C9: Multa e processos | D9: Credibilidade
A10: 1. Governança | B10: Integridade | C10: Ética e conduta | D10: Credibilidade
A11: 1. Governança | B11: Integridade | C11: Investigações e Acordo | D11: Credibilidade
A12: 1. Governança | B12: Integridade | C12: Controles internos / Prevenção à fraude e corrupção | D12: Credibilidade
A13: 1. Governança | B13: Integridade | C13: Demonstrações de resultados e auditoria | D13: Credibilidade
A14: 1. Governança | B14: Modelo de negócio | C14: Modelo Operacional Aegea | D14: Credibilidade
A15: 1. Governança | B15: Político-institucional | C15: Políticas públicas e setoriais | D15: Credibilidade
A16: 1. Governança | B16: Político-institucional | C16: Patrocínios | D16: Credibilidade
A17: 1. Governança | B17: Político-institucional | C17: Debate público versus privado | D17: Credibilidade
A18: 1. Governança | B18: Político-institucional | C18: Judicialização e CPIs | D18: Credibilidade
A19: 1. Governança | B19: Político-institucional | C19: Marco Legal do Saneamento
A20: 1. Governança | B20: Contratos e Regulação | C20: Agências reguladoras
A21: 1. Governança | B21: Político-institucional | C21: Agenda Associações (Politicas setoriais) | D21: Credibilidade
A22: 2. Eficiência Operacional e Qualidade | B22: Água Abastecimento | C22: Frequência, Continuidade | D22: Legitimidade
A23: 2. Eficiência Operacional e Qualidade | B23: Água Abastecimento | C23: Perdas, fraudes, furtos e ligações irregulares | D23: Legitimidade
A24: 2. Eficiência Operacional e Qualidade | B24: Água Abastecimento | C24: Rompimento de adutora | D24: Legitimidade
A25: 2. Eficiência Operacional e Qualidade | B25: Água Abastecimento | C25: Plano de contingência e redundância | D25: Legitimidade
A26: 2. Eficiência Operacional e Qualidade | B26: Água Abastecimento | C26: Informativo sobre abastecimento | D26: Legitimidade | E26: Talvez tirar, estava informativo
A27: 2. Eficiência Operacional e Qualidade | B27: Água Qualidade | C27: Gestão da qualidade da água | D27: Legitimidade
A28: 2. Eficiência Operacional e Qualidade | B28: Água Qualidade | C28: Monitoramento e controle de qualidade da água | D28: Legitimidade
A29: 2. Eficiência Operacional e Qualidade | B29: Água Qualidade | C29: Potabilidade | D29: Legitimidade
A30: 2. Eficiência Operacional e Qualidade | B30: Esgoto | C30: Rede e Coleta de esgoto | D30: Legitimidade
A31: 2. Eficiência Operacional e Qualidade | B31: Esgoto | C31: Tratamento de esgoto | D31: Legitimidade
A32: 2. Eficiência Operacional e Qualidade | B32: Esgoto | C32: Lançamento irregular e extravazamento | D32: Legitimidade
A33: 2. Eficiência Operacional e Qualidade | B33: Esgoto | C33: Balneabilidade | D33: Legitimidade
A34: 2. Eficiência Operacional e Qualidade | B34: Obras e intervenções | C34: Custos e eficiência | D34: Credibilidade
A35: 2. Eficiência Operacional e Qualidade | B35: Obras e intervenções | C35: Acidentes e danos a terceiros | D35: Credibilidade
A36: 2. Eficiência Operacional e Qualidade | B36: Obras e intervenções | C36: Expansão da rede | D36: Credibilidade
A37: 2. Eficiência Operacional e Qualidade | B37: Obras e intervenções | C37: Pavimentação e recomposição | D37: Credibilidade
A38: 2. Eficiência Operacional e Qualidade | B38: Obras e intervenções | C38: Manutenção, interdicções e transtornos urbanos | D38: Credibilidade
... A41: 2. Eficiência Operacional e Qualidade | B41: Atendimento ao cliente | C41: Órgãos de defesa ao cliente (Ouvidoria, Procon, Reclame Aqui, etc) | D41: Credibilidade
A42: 2. Eficiência Operacional e Qualidade | B42: Faturamento e cobrança | C42: Medição e leitura
A43: 2. Eficiência Operacional e Qualidade | B43: Faturamento e cobrança | C43: Conta errada, Tarifa abusiva
A44: 2. Eficiência Operacional e Qualidade | B44: Faturamento e cobrança | C44: Inadimplência, Corte e religação
A45: 2. Eficiência Operacional e Qualidade | B45: Segurança operacional e patrimonial | C45: Segurança, ameaças e invasões
A46: 3. Crescimento e Solidez Financeira | B46: Tarifa | C46: Reajuste/ Revisão tarifária
A47: 3. Crescimento e Solidez Financeira | B47: Tarifa | C47: Estrutura e composição tarifária
A48: 3. Crescimento e Solidez Financeira | B48: Desempenho financeiro | C48: Resultados financeiros e operacionais
A49: 3. Crescimento e Solidez Financeira | B49: Desempenho financeiro | C49: Projeções e guidance
A50: 3. Crescimento e Solidez Financeira | B50: Estrutura de capital | C50: Endividamento e alavancagem
A51: 3. Crescimento e Solidez Financeira | B51: Estrutura de capital | C51: Aportes dos acionistas
A52: 3. Crescimento e Solidez Financeira | B52: Estrutura de capital | C52: Dividendos e distribuição de capital
A53: 3. Crescimento e Solidez Financeira | B53: Estrutura de capital | C53: Emissão de dívida / Debêntures e bonds
... A63: 3. Crescimento e Solidez Financeira | B63: Economia circular | C63: Reúso de água
A64: 4. Responsabilidade Social | B64: Ações Sociais | C64: Programas sociais e comunidade | D64: Confiança
A65: 4. Responsabilidade Social | B65: Inclusão sanitária / Acessibilidade econômica | C65: Tarifa social
A66: 4. Responsabilidade Social | B66: Inclusão sanitária / Acessibilidade econômica | C66: Cadastro e elegibilidade
A67: 4. Responsabilidade Social | B67: Inclusão sanitária / Acessibilidade econômica | C67: Renegociação e apoio ao cliente
A68: 4. Responsabilidade Social | B68: Relacionamento comunitário | C68: Patrocínios incentivados
A69: 4. Responsabilidade Social | B69: Educação e conscientização | C69: Educação ambiental / Engajamento em saneamento e saúde / Uso consciente da água
A70: 4. Responsabilidade Social | B70: Pessoas | C70: Contratação | D70: Confiança
A71: 4. Responsabilidade Social | B71: Pessoas | C71: Atração e desenvolvimento | D71: Confiança
A72: 4. Responsabilidade Social | B72: Pessoas | C72: Equidade, Diversidade e inclusão | D72: Confiança
A73: 4. Responsabilidade Social | B73: Pessoas | C73: Segurança, condições e relações de trabalho | D73: Confiança
A74: 4. Responsabilidade Social | B74: Pessoas | C74: Cultura organizacional
A75: 4. Responsabilidade Social | B75: Saúde e segurança | C75: Segurança dos trabalhadores / Acidentes de trabalho
A76: 4. Responsabilidade Social | B76: Relações de trabalho | C76: Relações sindicais
A77: 4. Responsabilidade Social | B77: Relações de trabalho | C77: Terceirizados
A78: 5. Responsabilidade Ambiental | B78: Proteção ambiental | C78: Proteção de mananciais / Recuperação ambiental | D78: Confiança
A79: 5. Responsabilidade Ambiental | B79: Proteção ambiental | C79: Oceanos | D79: Confiança
A80: 5. Responsabilidade Ambiental | B80: Meio ambiente e clima | C80: Resiliência hídrica e novas fontes | D80: Confiança
A81: 5. Responsabilidade Ambiental | B81: Energia | C81: Eficiência energética / Energia renovável / Autoprodução e geração distribuída | D81: Confiança
A82: 5. Responsabilidade Ambiental | B82: Mudanças climáticas | C82: Emissão gases efeito estufa | D82: Confiança
A83: 5. Responsabilidade Ambiental | B83: Mudanças climáticas | C83: Eventos Climáticos
A84: 5. Responsabilidade Ambiental | B84: Mudanças climáticas | C84: Adaptação e resiliência
A85: 5. Responsabilidade Ambiental | B85: Proteção ambiental | C85: Biodiversidade
A86: 5. Responsabilidade Ambiental | B86: Licenciamento ambiental | C86: Licenças e autorizações / Condicionantes ambientais / Fiscalização e autuações
A87: 5. Responsabilidade Ambiental | B87: Economia circular e reúso | C87: Aproveitamento de subprodutos
A88: 5. Responsabilidade Ambiental | B88: Economia circular e reúso | C88: Gestão de lodo
A89: 5. Responsabilidade Ambiental | B89: Economia circular e reúso | C89: Redução e valorização de resíduos
A90: 6. Inovação e Tecnologia | B90: Tecnologia operação | C90: Monitoramento em tempo real | D90: Credibilidade
A91: 6. Inovação e Tecnologia | B91: Tecnologia operação | C91: Gestão de ativos | D91: Credibilidade
A92: 6. Inovação e Tecnologia | B92: Tecnologia operação | C92: Sensoriamento e telemetria | D92: Credibilidade
A93: 6. Inovação e Tecnologia | B93: Automação e inteligência artificial | C93: Automação de processos | D93: Credibilidade
A94: 6. Inovação e Tecnologia | B94: Automação e inteligência artificial | C94: Inteligência artificial / Eficiência baseada em dados / Análise preditiva | D94: Credibilidade
A95: 6. Inovação e Tecnologia | B95: Experiência digital do cliente | C95: Canais digitais / Autoatendimento | D95: Credibilidade
A96: 6. Inovação e Tecnologia | B96: Experiência digital do cliente | C96: Medição e fatura digital | D96: Credibilidade
A97: 6. Inovação e Tecnologia | B97: Pesquisa e desenvolvimento | C97: Novas tecnologias | D97: Credibilidade
A98: 6. Inovação e Tecnologia | B98: Pesquisa e desenvolvimento | C98: Parcerias com universidades e startups | D98: Credibilidade
A99: 6. Inovação e Tecnologia | B99: Segurança da informação | C99: Proteção de dados / Privacidade / Cybersegurança / Continuidade tecnológica | D99: Credibilidade
A100: 7. Prosperidade Compartilhada | B100: Universalização | C100: Universalização e metas de cobertura
A101: 7. Prosperidade Compartilhada | B101: Investimento em infraestrutura | C101: Volume de investimentos
A102: 7. Prosperidade Compartilhada | B102: Legado e impacto | C102: Benefícios do saneamento (saúde, educação, imoveis, socieconomico, etc)
A103: 7. Prosperidade Compartilhada | B103: Emprego e renda | C103: Geração de empregos / Contratação local / Capacitação profissional
A104: 7. Prosperidade Compartilhada | B104: Cadeia de valor | C104: Desenvolvimento de fornecedores / Fornecedores locais / Compras responsáveis

Sheet De-para Risk tracking
A1: # | B1: Nível 1: Pilar reputacional | C1: Nível 2: Tema estratégico | D1: Nível 3: Subtema | E1: LSO | F1: Domínio de risco | G1: Risk tracking (risco primário) | H1: Severidade | I1: Risco secundário | J1: Por que esse de-para | K1: Exemplo de notícia que se enquadra no risco e no subtema | L1: Origem do exemplo | M1: Validação Aegea (concorda S/N) | N1: Ajuste proposto pela área
A2: 1 | B2: 1. Governança | C2: Governança corporativa | D2: Estrutura de governança / Conselho e comitês | E2: Credibilidade | F2: — | G2: Sem enquadramento | H2: — | J2: Narrativa institucional. Não existe risco corporativo equivalente entre os 32 clusters. A ausência é deliberada, não é lacuna de mapeamento. | K2: Não se aplica. Notícia negativa sobre conselho ou alta administração é registrada em Ética e conduta ou em Acionistas, que têm cluster de risco. | L2: —
A3: 2 | B3: 1. Governança | C3: Governança corporativa | D3: Acionistas | E3: Credibilidade | F3: Riscos Geopolíticos e Estratégicos | G3: Gestão de Portfólio e Estrutura de Capital | H3: Alto | I3: Integridade das Informações ao Mercado | J3: Movimento de composição acionária e de controle atinge primeiro a estrutura de capital e o portfólio, antes de qualquer outro eixo. | K3: Negociação de venda de participação de acionista relevante do grupo, com especulação de mudança de controle em veículo econômico. | L3: Exemplo típico (premissa Peers)
A4: 3 | B4: 1. Governança | C4: Contratos e Regulação | D4: Cumprimento contratual | E4: Legitimidade | F4: Riscos Geopolíticos e Estratégicos | G4: Legal e Regulatório | H4: Moderado | I4: Gestão de Contratos e Terceiros | J4: Descumprimento de contrato de concessão é evento regulatório, com sanção e risco de caducidade. O dano se materializa no eixo legal. | K4: Agência reguladora notifica a concessionária por não atingir metas de cobertura previstas no contrato, com abertura de processo sancionador. | L4: Exemplo típico (premissa Peers)
A5: 4 | B5: 1. Governança | C5: Contratos e Regulação | D5: Revisão e renovação de contratos | E5: Legitimidade | F5: Riscos Geopolíticos e Estratégicos | G5: Legal e Regulatório | H5: Moderado | I5: Assunção de novos negócios | J5: Revisão e prorrogação tramitam no poder concedente e no regulador, mesmo quando a motivação é comercial. | K5: Câmara municipal discute aditivo de prorrogação do contrato e vereadores pedem suspensão da assinatura. | L5: Exemplo típico (premissa Peers)
A6: 5 | B6: 1. Governança | C6: Contratos e Regulação | D6: Reequilíbrio econômico-financeiro | E6: Legitimidade | F6: Riscos Geopolíticos e Estratégicos | G6: Legal e Regulatório | H6: Moderado | I6: Contingências e Provisões | J6: Pleito de reequilíbrio é disputa regulatória, com desdobramento em provisão quando vira litígio. | K6: Prefeitura contesta publicamente o pleito de reequilíbrio apresentado pela concessionária e aciona a agência reguladora. | L6: Exemplo típico (premissa Peers)
A7: 6 | B7: 1. Governança | C7: Contratos e Regulação | D7: Segurança jurídica | E7: Legitimidade | F7: Riscos Geopolíticos e Estratégicos | G7: Legal e Regulatório | H7: Moderado | I7: Instabilidade Política / Econômica | J7: Estabilidade das regras do contrato. Tangencia instabilidade política quando a origem é troca de governo. | K7: Nova gestão municipal anuncia revisão do contrato de concessão assinado pela gestão anterior. | L7: Exemplo típico (premissa Peers)
A8: 7 | B8: 1. Governança | C8: Contratos e Regulação | D8: Fiscalização regulatória | E8: Legitimidade | F8: Riscos Geopolíticos e Estratégicos | G8: Legal e Regulatório | H8: Moderado | I8: Relações Institucionais e Governamentais | J8: Ato do regulador contra a empresa é risco legal. A relação institucional com a agência fica como leitura secundária. | K8: Agência reguladora abre fiscalização extraordinária após série de interrupções de abastecimento em município atendido. | L8: Exemplo típico (premissa Peers)
A9: 8 | B9: 1. Governança | C9: Contratos e Regulação | D9: Multa e processos | E9: Credibilidade | F9: Riscos com Finanças e Contabilidade | G9: Contingências e Provisões | H9: Moderado | I9: Legal e Regulatório | J9: Multa aplicada e processo em curso são passivo mensurável. Entram pelo eixo de contingência e provisão. | K9: Concessionária é multada pelo regulador por descumprimento de prazo de atendimento e recorre da decisão. | L9: Exemplo típico (premissa Peers)
A10: 9 | B10: 1. Governança | C10: Integridade | D10: Ética e conduta | E10: Credibilidade | F10: Riscos Geopolíticos e Estratégicos | G10: Práticas Ilegais ou Antiéticas | H10: Alto | J10: Conduta individual ou corporativa questionada. Núcleo do risco de integridade. | K10: Reportagem aponta suposto conflito de interesse entre executivo da concessionária e fornecedor contratado. | L10: Exemplo típico (premissa Peers)
A11: 10 | B11: 1. Governança | C11: Integridade | D11: Investigações e Acordo | E11: Credibilidade | F11: Riscos Geopolíticos e Estratégicos | G11: Práticas Ilegais ou Antiéticas | H11: Alto | I11: Contingências e Provisões | J11: Investigação formal, delação e acordo de leniência. O desdobramento financeiro aparece em provisão. | K11: Ministério Público instaura inquérito sobre contratação de obra em SPE do grupo. | L11: Exemplo típico (premissa Peers)
A12: 11 | B12: 1. Governança | C12: Integridade | D12: Controles internos / Prevenção à fraude e corrupção | E12: Credibilidade | F12: Riscos Geopolíticos e Estratégicos | G12: Práticas Ilegais ou Antiéticas | H12: Alto | I12: Integridade das Demonstrações Financeiras | J12: Falha de controle interno é a causa-raiz típica do evento de integridade. | K12: Auditoria interna identifica fraude em processo de compras e o caso chega à imprensa antes do comunicado da empresa. | L12: Exemplo típico (premissa Peers)
A13: 12 | B13: 1. Governança | C13: Integridade | D13: Demonstrações de resultados e auditoria | E13: Credibilidade | F13: Riscos com Finanças e Contabilidade | G13: Integridade das Demonstrações Financeiras | H13: Moderado | I13: Integridade das Informações ao Mercado | J13: Ressalva de auditoria e republicação de demonstração atacam diretamente a integridade contábil. | K13: Auditoria externa emite ressalva sobre reconhecimento de receita nas demonstrações do grupo. | L13: Exemplo típico (premissa Peers)
A14: 13 | B14: 1. Governança | C14: Modelo de negócio | D14: Modelo Operacional Aegea | E14: Credibilidade | F14: — | G14: Sem enquadramento | H14: — | J14: Narrativa de posicionamento institucional. Sem risco corporativo equivalente na matriz. | K14: Não se aplica. Crítica ao modelo privado de operação é registrada em Debate público versus privado. | L14: —
A15: 14 | B15: 1. Governança | C15: Político-institucional | D15: Políticas públicas e setoriais | E15: Credibilidade | F15: Riscos Geopolíticos e Estratégicos | G15: Instabilidade Política / Econômica | H15: Moderado | I15: Relações Institucionais e Governamentais | J15: Mudança de política setorial altera as regras do negócio e tem origem política, não operacional. | K15: Governo federal sinaliza mudança na regra de financiamento do saneamento e analistas apontam efeito sobre concessionárias privadas. | L15: Exemplo típico (premissa Peers)
A16: 15 | B16: 1. Governança | C16: Político-institucional | D16: Patrocínios institucionais | E16: Credibilidade | F16: Riscos Geopolíticos e Estratégicos | G16: Relações Institucionais e Governamentais | H16: Moderado | I16: Práticas Ilegais ou Antiéticas | J16: Patrocínio a ente público, evento ou veículo. Risco residual de leitura como influência indevida. | K16: Patrocínio de festival, carnaval e réveillon citado em veículos locais, incluindo agradecimento de locutor de rádio pelo apoio ao programa. Trinta e três ocorrências no lote auditado de janeiro. | L16: Base jan/2026 (Clipei)
A17: 16 | B17: 1. Governança | C17: Político-institucional | D17: Debate público versus privado | E17: Credibilidade | F17: Riscos Geopolíticos e Estratégicos | G17: Instabilidade Política / Econômica | H17: Moderado | I17: Relações com as Comunidades | J17: Debate ideológico sobre privatização do saneamento. Vetor político, com repercussão comunitária. | K17: Artigo de opinião defende reestatização do serviço e cita a concessionária como exemplo de fracasso da concessão. | L17: Exemplo típico (premissa Peers)
A18: 17 | B18: 1. Governança | C18: Político-institucional | D18: Judicialização e CPIs | E18: Credibilidade | F18: Riscos Geopolíticos e Estratégicos | G18: Legal e Regulatório | H18: Moderado | I18: Relações Institucionais e Governamentais | J18: CPI e ação judicial contra a concessão são instrumento jurídico com motor político. | K18: Câmara municipal aprova abertura de CPI para investigar a execução do contrato de concessão. | L18: Exemplo típico (premissa Peers)
A19: 18 | B19: 1. Governança | C19: Político-institucional | D19: Marco Legal do Saneamento | F19: Riscos Geopolíticos e Estratégicos | G19: Instabilidade Política / Econômica | H19: Moderado | I19: Legal e Regulatório | J19: Alteração do marco é decisão do Legislativo. Vira risco legal quando a norma já está vigente e passa a obrigar. | K19: Proposta em tramitação no Congresso flexibiliza metas do Marco Legal e reportagem cita a concessionária entre as afetadas. | L19: Exemplo típico (premissa Peers)
A20: 19 | B20: 1. Governança | C20: Contratos e Regulação | D20: Agências reguladoras | F20: Riscos Geopolíticos e Estratégicos | G20: Relações Institucionais e Governamentais | H20: Moderado | I20: Legal e Regulatório | J20: Subtema de relacionamento institucional. O ato sancionatório do regulador fica em Fiscalização regulatória, para não duplicar. | K20: Troca da diretoria da agência reguladora estadual é noticiada com menção às concessões sob fiscalização. | L20: Exemplo típico (premissa Peers)
A21: 20 | B21: 1. Governança | C21: Político-institucional | D21: Agenda Associações (Políticas setoriais) | E21: Credibilidade | F21: Riscos Geopolíticos e Estratégicos | G21: Relações Institucionais e Governamentais | H21: Moderado | I21: Instabilidade Política / Econômica | J21: Atuação associativa é posicionamento setorial coletivo. Risco de leitura como defesa de interesse contra o usuário. | K21: Associação setorial divulga nota contra mudança na regra tarifária e é acusada de representar interesse das concessionárias. | L21: Exemplo típico (premissa Peers)
A22: 21 | B22: 2. Eficiência Operacional e Qualidade | C22: Abastecimento de água | D22: Frequência, Continuidade | E22: Legitimidade | F22: Riscos Operacionais | G22: Entrega de água e tratamento de esgoto | H22: Critico | I22: Relações com as Comunidades | J22: Falta de água é o fato reputacional mais recorrente do setor e aciona diretamente o risco Crítico de entrega. | K22: Falta de água em bairros atendidos pela concessionária, com reclamação de moradores em veículo local. Na base de janeiro, parte desses registros estava rotulada pela clipadora como fato relevante. | L22: Base jan/2026 (Clipei)
A23: 22 | B23: 2. Eficiência Operacional e Qualidade | C23: Abastecimento de água | D23: Perdas, fraudes, furtos e ligações irregulares | E23: Legitimidade | F23: Riscos Operacionais | G23: Integridade e Confiabilidade dos Ativos | H23: Alto | I23: Gestão ESG e Sustentabilidade | J23: Índice de perdas e furto são lidos como falha de confiabilidade do ativo e como desperdício de recurso natural. | K23: Furto de hidrômetro em bairro, registro presente na base de janeiro e também rotulado como fato relevante. | L23: Base jan/2026 (Clipei)
A24: 23 | B24: 2. Eficiência Operacional e Qualidade | C24: Abastecimento de água | D24: Rompimento de adutora | E24: Legitimidade | F24: Riscos Operacionais | G24: Integridade e Confiabilidade dos Ativos | H24: Alto | I24: Entrega de água e tratamento de esgoto | J24: Falha estrutural de ativo crítico, com desabastecimento e dano a terceiro ao mesmo tempo. | K24: Rompimento de adutora deixa municípios sem água e provoca alagamento em via pública. | L24: Exemplo típico (premissa Peers)
A25: 24 | B25: 2. Eficiência Operacional e Qualidade | C25: Abastecimento de água | D25: Plano de contingência e redundância | E25: Legitimidade | F25: Riscos com Stakeholders e novos negócios | G25: Gestão de Crises | H25: Critico | I25: Integridade e Confiabilidade dos Ativos | J25: Único subtema que endereça diretamente o cluster de Gestão de Crises, que é Crítico. Ver aba Pontos de atenção. | K25: Após mais de 48 horas de desabastecimento, a imprensa questiona a existência e a efetividade do plano de contingência da concessionária. | L25: Exemplo típico (premissa Peers)
A26: 25 | B26: 2. Eficiência Operacional e Qualidade | C26: Qualidade da água | D26: Gestão da qualidade da água | E26: Legitimidade | F26: Riscos Operacionais | G26: Entrega de água e tratamento de esgoto | H26: Critico | I26: Saúde e Segurança | J26: Qualidade da água combina saúde pública e prova técnica. Severidade máxima na entrega. | K26: Laudo de vigilância sanitária aponta água fora do padrão de potabilidade em ponto da rede de distribuição. | L26: Exemplo típico (premissa Peers)
A27: 26 | B27: 2. Eficiência Operacional e Qualidade | C27: Qualidade da água | D27: Monitoramento e controle de qualidade da água | E27: Legitimidade | F27: Riscos Operacionais | G27: Entrega de água e tratamento de esgoto | H27: Critico | I27: Gestão de Licenças | J27: Falha ou atraso na divulgação converte evento técnico em suspeita de ocultação de informação. | K27: Reportagem aponta atraso na publicação dos resultados de análise de qualidade da água exigidos por norma. | L27: Exemplo típico (premissa Peers)
A28: 27 | B28: 2. Eficiência Operacional e Qualidade | C28: Qualidade da água | D28: Potabilidade | E28: Legitimidade | F28: Riscos Operacionais | G28: Entrega de água e tratamento de esgoto | H28: Critico | I28: Saúde e Segurança | J28: Aciona vigilância sanitária e tem potencial de dano irreversível à licença social de operar. | K28: Moradores relatam água turva e com odor; vigilância sanitária coleta amostras e o caso vira pauta regional. | L28: Exemplo típico (premissa Peers)
A29: 28 | B29: 2. Eficiência Operacional e Qualidade | C29: Esgoto | D29: Rede e Coleta de esgoto | E29: Legitimidade | F29: Riscos Operacionais | G29: Entrega de água e tratamento de esgoto | H29: Critico | I29: Relações com as Comunidades | J29: Cobertura e falha de coleta são o núcleo do risco Crítico de entrega. | K29: Bairro segue sem rede de esgoto apesar da meta contratual e moradores cobram a concessionária em audiência pública. | L29: Exemplo típico (premissa Peers)
A30: 29 | B30: 2. Eficiência Operacional e Qualidade | C30: Esgoto | D30: Tratamento de esgoto | E30: Legitimidade | F30: Riscos Operacionais | G30: Entrega de água e tratamento de esgoto | H30: Critico | I30: Meio ambiente operacional | J30: Tratamento inadequado é simultaneamente falha de entrega e poluição. | K30: Estação de tratamento opera abaixo da capacidade e esgoto sem tratamento chega a corpo hídrico. | L30: Exemplo típico (premissa Peers)
A31: 30 | B31: 2. Eficiência Operacional e Qualidade | C31: Esgoto | D31: Lançamento irregular e extravasamento | E31: Legitimidade | F31: Riscos Operacionais | G31: Meio ambiente operacional | H31: Alto | I31: Gestão de Licenças | J31: Poluição local com autuação ambiental provável. O dano é ambiental antes de ser de serviço. | K31: Extravasamento de esgoto em via pública gera autuação do órgão ambiental estadual. | L31: Exemplo típico (premissa Peers)
A32: 31 | B32: 2. Eficiência Operacional e Qualidade | C32: Esgoto | D32: Balneabilidade | E32: Legitimidade | F32: Riscos Operacionais | G32: Meio ambiente operacional | H32: Alto | I32: Relações com as Comunidades | J32: Impacto ambiental visível e de apelo público alto, em especial no litoral. | K32: Boletim de balneabilidade da Fepam replicado por dezenas de portais do Rio Grande do Sul. Maior bloco unitário do lote auditado de janeiro, 50 títulos, hoje rotulados como licença ambiental. | L32: Base jan/2026 (Clipei)
A33: 32 | B33: 2. Eficiência Operacional e Qualidade | C33: Esgoto | D33: Odor e incômodo | F33: Riscos ESG | G33: Relações com as Comunidades | H33: Alto | I33: Meio ambiente operacional | J33: Incômodo de vizinhança. O dano se materializa na relação com a comunidade do entorno. | K33: Moradores do entorno de estação elevatória reclamam de mau cheiro recorrente e acionam a prefeitura. | L33: Exemplo típico (premissa Peers)
A34: 33 | B34: 2. Eficiência Operacional e Qualidade | C34: Obras e intervenções | D34: Custos e eficiência | E34: Credibilidade | F34: Riscos em Investimentos de Capital | G34: Gestão de Contratos e Terceiros | H34: Moderado | I34: Gestão de Portfólio e Estrutura de Capital | J34: Desvio de custo e de prazo de obra remete à gestão de contratos e de terceiros. | K34: Tribunal de contas aponta sobrepreço e atraso em obra de saneamento executada por terceiro contratado. | L34: Exemplo típico (premissa Peers)
A35: 34 | B35: 2. Eficiência Operacional e Qualidade | C35: Obras e intervenções | D35: Acidentes e danos a terceiros | E35: Credibilidade | F35: Riscos Operacionais | G35: Saúde e Segurança | H35: Alto | I35: Gestão de Contratos e Terceiros | J35: Acidente em obra com vítima ou dano patrimonial a terceiro é evento de saúde e segurança. | K35: Vala de obra sem sinalização provoca acidente com motociclista; o serviço era executado por empresa terceirizada. | L35: Exemplo típico (premissa Peers)
A36: 35 | B36: 2. Eficiência Operacional e Qualidade | C36: Obras e intervenções | D36: Expansão da rede | E36: Credibilidade | F36: Riscos em Investimentos de Capital | G36: Gestão de Contratos e Terceiros | H36: Moderado | I36: Gestão Ambiental em Projetos e Obras | J36: Execução de capex. Atraso de expansão também tem leitura de meta contratual. | K36: Cronograma de expansão da rede não é cumprido e a prefeitura cobra a concessionária publicamente. | L36: Exemplo típico (premissa Peers)
A37: 36 | B37: 2. Eficiência Operacional e Qualidade | C37: Obras e intervenções | D37: Pavimentação e recomposição | E37: Credibilidade | F37: Riscos em Investimentos de Capital | G37: Gestão de Contratos e Terceiros | H37: Moderado | I37: Relações com as Comunidades | J37: Falha de recomposição é a reclamação de obra mais frequente e costuma ser responsabilidade do terceiro executor. | K37: Buracos deixados após obra da concessionária permanecem meses sem recomposição e viram pauta de veículo local. | L37: Exemplo típico (premissa Peers)
A38: 37 | B38: 2. Eficiência Operacional e Qualidade | C38: Obras e intervenções | D38: Manutenção, interdições e transtornos urbanos | E38: Credibilidade | F38: Riscos ESG | G38: Relações com as Comunidades | H38: Alto | I38: Gestão de Contratos e Terceiros | J38: Transtorno urbano é o canal direto de deterioração da relação com a comunidade. | K38: Interdição de avenida para manutenção de rede gera congestionamento e reclamação de comerciantes. | L38: Exemplo típico (premissa Peers)
A39: 38 | B39: 2. Eficiência Operacional e Qualidade | C39: Atendimento ao cliente | D39: Canais de atendimento | E39: Credibilidade | F39: Riscos com Clientes | G39: Regularidade, Atendimento e Satisfação | H39: Alto | J39: Disponibilidade e tempo de resposta dos canais. Dano registrado no risco com clientes. | K39: Reportagem mostra tempo de espera no call center durante episódio de falta de água. | L39: Exemplo típico (premissa Peers)
A40: 39 | B40: 2. Eficiência Operacional e Qualidade | C40: Atendimento ao cliente | D40: Atendimento ao cliente | E40: Credibilidade | F40: Riscos com Clientes | G40: Regularidade, Atendimento e Satisfação | H40: Alto | J40: Qualidade e resolutividade do atendimento prestado. | K40: Cliente relata três meses sem solução para vazamento na calçada, mesmo com protocolo aberto. | L40: Exemplo típico (premissa Peers)
A41: 40 | B41: 2. Eficiência Operacional e Qualidade | C41: Atendimento ao cliente | D41: Órgãos de defesa ao cliente (Ouvidoria, Procon, Reclame Aqui) | E41: Credibilidade | F41: Riscos com Clientes | G41: Regularidade, Atendimento e Satisfação | H41: Alto | I41: Legal e Regulatório | J41: Acionamento de órgão de defesa é o indicador externo do risco com clientes. | K41: Procon notifica a concessionária após aumento das reclamações sobre cobrança e interrupção de serviço. | L41: Exemplo típico (premissa Peers)
A42: 41 | B42: 2. Eficiência Operacional e Qualidade | C42: Faturamento e cobrança | D42: Medição e leitura | F42: Riscos com Clientes | G42: Regularidade, Atendimento e Satisfação | H42: Alto | J42: Erro de medição é a origem da maior parte da contestação de conta. | K42: Moradores recebem conta com consumo estimado por falta de leitura do hidrômetro. | L42: Exemplo típico (premissa Peers)
A43: 42 | B43: 2. Eficiência Operacional e Qualidade | C43: Faturamento e cobrança | D43: Conta errada, Tarifa abusiva | F43: Riscos com Clientes | G43: Regularidade, Atendimento e Satisfação | H43: Alto | I43: Legal e Regulatório | J43: Contestação de fatura. Vira risco regulatório quando a crítica recai sobre a tarifa homologada. | K43: Série de contas com valor muito acima da média vira pauta em veículo local e gera mutirão do Procon. | L43: Exemplo típico (premissa Peers)
A44: 43 | B44: 2. Eficiência Operacional e Qualidade | C44: Faturamento e cobrança | D44: Inadimplência, Corte e religação | F44: Riscos com Clientes | G44: Gestão de Crédito e Inadimplência | H44: Moderado | I44: Relações com as Comunidades | J44: Corte em serviço essencial é o enquadramento típico de direito à água, com alta sensibilidade comunitária. | K44: Corte de abastecimento em residência com morador em tratamento de saúde gera ação judicial e repercussão local. | L44: Exemplo típico (premissa Peers)
A45: 44 | B45: 2. Eficiência Operacional e Qualidade | C45: Segurança operacional e patrimonial | D45: Segurança, ameaças e invasões | F45: Riscos Operacionais | G45: Integridade e Confiabilidade dos Ativos | H45: Alto | I45: Saúde e Segurança | J45: Invasão e vandalismo em ativo operacional. Não existe cluster de segurança patrimonial na matriz. | K45: Furto de cabos em estação de tratamento interrompe a operação e provoca desabastecimento. | L45: Exemplo típico (premissa Peers)
A46: 45 | B46: 3. Crescimento e Solidez Financeira | C46: Tarifa | D46: Reajuste/ Revisão tarifária | F46: Riscos Geopolíticos e Estratégicos | G46: Legal e Regulatório | H46: Moderado | I46: Relações com as Comunidades | J46: Reajuste é ato regulatório homologado. A repercussão pública é leitura secundária. | K46: Agência homologa reajuste anual e vereadores pedem suspensão do aumento na Justiça. | L46: Exemplo típico (premissa Peers)
A47: 46 | B47: 3. Crescimento e Solidez Financeira | C47: Tarifa | D47: Estrutura e composição tarifária | F47: Riscos Geopolíticos e Estratégicos | G47: Legal e Regulatório | H47: Moderado | I47: Regularidade, Atendimento e Satisfação | J47: Desenho da tarifa e subsídio cruzado são decisão regulatória. | K47: Reportagem compara a tarifa da concessionária com a de operadores públicos vizinhos e questiona a diferença. | L47: Exemplo típico (premissa Peers)
A48: 47 | B48: 3. Crescimento e Solidez Financeira | C48: Desempenho financeiro | D48: Resultados financeiros e operacionais | F48: Riscos com Stakeholders e novos negócios | G48: Integridade das Informações ao Mercado | H48: Moderado | I48: Integridade das Demonstrações Financeiras | J48: Divulgação de resultado ao mercado. O risco é de integridade da informação prestada. | K48: Divulgação de resultado trimestral com queda de margem é destacada pela imprensa econômica. | L48: Exemplo típico (premissa Peers)
A49: 48 | B49: 3. Crescimento e Solidez Financeira | C49: Desempenho financeiro | D49: Projeções e guidance | F49: Riscos com Stakeholders e novos negócios | G49: Integridade das Informações ao Mercado | H49: Moderado | I49: Gestão de Portfólio e Estrutura de Capital | J49: Guidance não entregue é risco de credibilidade junto a investidores e credores. | K49: Analistas apontam que a companhia não executou o capex projetado para o ano. | L49: Exemplo típico (premissa Peers)
A50: 49 | B50: 3. Crescimento e Solidez Financeira | C50: Estrutura de capital | D50: Endividamento e alavancagem | F50: Riscos Geopolíticos e Estratégicos | G50: Liquidez, Gestão da Dívida e Quebra de Covenants de financiamentos | H50: Alto | I50: Gestão de Portfólio e Estrutura de Capital | J50: Nível de alavancagem é o indicador central do risco de liquidez. | K50: Reportagem destaca alavancagem do grupo acima do histórico e concentração de vencimentos no curto prazo. | L50: Exemplo típico (premissa Peers)
A51: 50 | B51: 3. Crescimento e Solidez Financeira | C51: Estrutura de capital | D51: Aportes dos acionistas | F51: Riscos Geopolíticos e Estratégicos | G51: Gestão de Portfólio e Estrutura de Capital | H51: Alto | I51: Liquidez, Gestão da Dívida e Quebra de Covenants de financiamentos | J51: Capacidade e disposição dos acionistas de aportar é decisão de portfólio antes de ser de caixa. | K51: Notícia sobre necessidade de novo aporte dos acionistas em SPE do grupo para sustentar o plano de investimento. | L51: Exemplo típico (premissa Peers)
A52: 51 | B52: 3. Crescimento e Solidez Financeira | C52: Estrutura de capital | D52: Dividendos e distribuição de capital | F52: Riscos Geopolíticos e Estratégicos | G52: Gestão de Portfólio e Estrutura de Capital | H52: Alto | I52: Liquidez, Gestão da Dívida e Quebra de Covenants de financiamentos | J52: Política de distribuição afeta estrutura de capital e caixa disponível para investimento. | K52: Distribuição de dividendos é questionada diante do volume de investimento contratado ainda não executado. | L52: Exemplo típico (premissa Peers)
A53: 52 | B53: 3. Crescimento e Solidez Financeira | C53: Estrutura de capital | D53: Emissão de dívida / Debêntures e bonds | F53: Riscos Geopolíticos e Estratégicos | G53: Liquidez, Gestão da Dívida e Quebra de Covenants de financiamentos | H53: Alto | I53: Integridade das Informações ao Mercado | J53: Emissão malsucedida ou com custo acima do esperado sinaliza deterioração de crédito. | K53: Emissão de debêntures sai com taxa acima da referência e o mercado lê como piora da percepção de crédito. | L53: Exemplo típico (premissa Peers)
A54: 53 | B54: 3. Crescimento e Solidez Financeira | C54: Estrutura de capital | D54: IPO e acesso ao mercado de ações | F54: Riscos Geopolíticos e Estratégicos | G54: Gestão de Portfólio e Estrutura de Capital | H54: Alto | I54: Integridade das Informações ao Mercado | J54: Decisão de estrutura de capital e de portfólio dos acionistas. | K54: Imprensa econômica noticia adiamento do IPO do grupo por condição de mercado. | L54: Exemplo típico (premissa Peers)
A55: 54 | B55: 3. Crescimento e Solidez Financeira | C55: Crédito e rating | D55: Percepção de risco de crédito / Rating corporativo | F55: Riscos Geopolíticos e Estratégicos | G55: Liquidez, Gestão da Dívida e Quebra de Covenants de financiamentos | H55: Alto | I55: Integridade das Informações ao Mercado | J55: Rebaixamento encarece a dívida e pode acionar cláusula contratual. | K55: Agência de rating coloca a companhia em perspectiva negativa e cita alavancagem e capex. | L55: Exemplo típico (premissa Peers)
A56: 55 | B56: 3. Crescimento e Solidez Financeira | C56: Crédito e rating | D56: Covenants | F56: Riscos Geopolíticos e Estratégicos | G56: Liquidez, Gestão da Dívida e Quebra de Covenants de financiamentos | H56: Alto | J56: Quebra de covenant é o evento nomeado no próprio cluster de risco. | K56: Reportagem aponta risco de quebra de covenant financeiro em contrato de financiamento do grupo. | L56: Exemplo típico (premissa Peers)
A57: 56 | B57: 3. Crescimento e Solidez Financeira | C57: Crescimento e portfólio | D57: Novos Negócios e Leilões | F57: Riscos com Stakeholders e novos negócios | G57: Assunção de novos negócios | H57: Moderado | I57: Práticas Ilegais ou Antiéticas | J57: Disputa de leilão, com risco residual de conduta concorrencial, hoje sem subtema dedicado. | K57: Concorrente questiona na Justiça o resultado de leilão vencido pelo grupo. | L57: Exemplo típico (premissa Peers)
A58: 57 | B58: 3. Crescimento e Solidez Financeira | C58: Crescimento e portfólio | D58: M&A e parcerias | F58: Riscos com Stakeholders e novos negócios | G58: Assunção de novos negócios | H58: Moderado | I58: Gestão de Portfólio e Estrutura de Capital | J58: Aquisição e parceria, incluindo passivo herdado do ativo adquirido. | K58: Aquisição de operador regional traz passivo ambiental herdado, apontado em reportagem após o fechamento. | L58: Exemplo típico (premissa Peers)
A59: 58 | B59: 3. Crescimento e Solidez Financeira | C59: Crescimento e portfólio | D59: Venda de ativo | F59: Riscos Geopolíticos e Estratégicos | G59: Gestão de Portfólio e Estrutura de Capital | H59: Alto | I59: Liquidez, Gestão da Dívida e Quebra de Covenants de financiamentos | J59: Desinvestimento é decisão de portfólio, com leitura de liquidez. | K59: Negociação de venda de participação em concessão é noticiada antes do anúncio oficial ao mercado. | L59: Exemplo típico (premissa Peers)
A60: 59 | B60: 3. Crescimento e Solidez Financeira | C60: Crescimento e portfólio | D60: Entrada em novos mercados | F60: Riscos com Stakeholders e novos negócios | G60: Assunção de novos negócios | H60: Moderado | I60: Instabilidade Política / Econômica | J60: Nova geografia significa novo poder concedente e novo ambiente político. | K60: Entrada em novo estado gera reação de lideranças locais contrárias ao modelo de concessão. | L60: Exemplo típico (premissa Peers)
A61: 60 | B61: 3. Crescimento e Solidez Financeira | C61: Novos negócios | D61: Coleta de resíduos / Tratamento e Destinação | F61: Riscos Operacionais | G61: Tratamento de resíduos sólidos urbanos (RSU) | H61: Alto | I61: Meio ambiente operacional | J61: Linha de resíduos sólidos urbanos tem cluster próprio na matriz. | K61: Atraso na coleta de resíduos em município atendido pelo grupo gera acúmulo de lixo e reclamação. | L61: Exemplo típico (premissa Peers)
A62: 61 | B62: 3. Crescimento e Solidez Financeira | C62: Novos negócios | D62: Taxa de lixo | F62: Riscos Operacionais | G62: Tratamento de resíduos sólidos urbanos (RSU) | H62: Alto | I62: Relações com as Comunidades | J62: Cobrança da taxa é o ponto de atrito público da linha de resíduos. | K62: Cobrança da taxa de lixo junto à conta de água é contestada por moradores e por vereadores. | L62: Exemplo típico (premissa Peers)
A63: 62 | B63: 3. Crescimento e Solidez Financeira | C63: Novos negócios | D63: Reúso de água | F63: Riscos com Stakeholders e novos negócios | G63: Novas Tendências e Futuro | H63: Moderado | I63: Entrega de água e tratamento de esgoto | J63: Linha emergente. Hoje mais tendência de mercado do que operação em escala. | K63: Projeto de reúso anunciado não sai do papel e é cobrado pela imprensa local dois anos depois. | L63: Exemplo típico (premissa Peers)
A64: 63 | B64: 4. Responsabilidade Social | C64: Ações Sociais | D64: Programas sociais e comunidade | E64: Confiança | F64: Riscos ESG | G64: Relações com as Comunidades | H64: Alto | J64: Programa social contestado como propaganda ou como compensação por serviço mal prestado. | K64: Programa social da concessionária é criticado por liderança comunitária como compensação por falhas no abastecimento. | L64: Exemplo típico (premissa Peers)
A65: 64 | B65: 4. Responsabilidade Social | C65: Inclusão sanitária / Acessibilidade econômica | D65: Tarifa social | F65: Riscos ESG | G65: Relações com as Comunidades | H65: Alto | I65: Gestão de Crédito e Inadimplência | J65: Acesso econômico ao serviço. Falha de alcance da tarifa social vira questão comunitária. | K65: Reportagem mostra famílias elegíveis que não conseguem acessar a tarifa social no município. | L65: Exemplo típico (premissa Peers)
A66: 65 | B66: 4. Responsabilidade Social | C66: Inclusão sanitária / Acessibilidade econômica | D66: Cadastro e elegibilidade | F66: Riscos com Clientes | G66: Regularidade, Atendimento e Satisfação | H66: Alto | I66: Relações com as Comunidades | J66: Processo de cadastro e barreira de acesso ao benefício, operados pelo canal de atendimento. | K66: Exigência de documentos para cadastro na tarifa social é apontada como barreira de acesso. | L66: Exemplo típico (premissa Peers)
A67: 66 | B67: 4. Responsabilidade Social | C67: Inclusão sanitária / Acessibilidade econômica | D67: Renegociação e apoio ao cliente | F67: Riscos com Clientes | G67: Gestão de Crédito e Inadimplência | H67: Moderado | I67: Regularidade, Atendimento e Satisfação | J67: Política de renegociação de débito, que é gestão de crédito antes de ser atendimento. | K67: Campanha de renegociação é criticada pelos encargos cobrados no parcelamento da dívida. | L67: Exemplo típico (premissa Peers)
A68: 67 | B68: 4. Responsabilidade Social | C68: Relacionamento comunitário | D68: Prêmios, Projetos e incentivos à comunidade | F68: Riscos ESG | G68: Relações com as Comunidades | H68: Alto | J68: Investimento social privado, com risco residual de prêmio ou projeto contestado. | K68: Prêmio recebido pela concessionária é contestado por entidade local diante do volume de reclamações de serviço. | L68: Exemplo típico (premissa Peers)
A69: 68 | B69: 4. Responsabilidade Social | C69: Educação e conscientização | D69: Educação ambiental / Engajamento em saneamento e saúde / Uso consciente da água | F69: Riscos ESG | G69: Relações com as Comunidades | H69: Alto | I69: Gestão ESG e Sustentabilidade | J69: Programa educacional junto à comunidade e à rede escolar. | K69: Programa de educação ambiental em escolas é questionado como publicidade institucional disfarçada. | L69: Exemplo típico (premissa Peers)
A70: 69 | B70: 4. Responsabilidade Social | C70: Pessoas | D70: Contratação | E70: Confiança | F70: Riscos Geopolíticos e Estratégicos | G70: Gestão do Capital Humano | H70: Moderado | J70: Processo seletivo e contratação. Dano registrado em capital humano. | K70: Processo seletivo é questionado por candidatos em veículo local por falta de transparência nos critérios. | L70: Exemplo típico (premissa Peers)
A71: 70 | B71: 4. Responsabilidade Social | C71: Pessoas | D71: Atração e desenvolvimento | E71: Confiança | F71: Riscos Geopolíticos e Estratégicos | G71: Gestão do Capital Humano | H71: Moderado | J71: Retenção e desenvolvimento de talento. | K71: Reportagem aponta rotatividade alta na operação regional do grupo. | L71: Exemplo típico (premissa Peers)
A72: 71 | B72: 4. Responsabilidade Social | C72: Pessoas | D72: Equidade, Diversidade e inclusão | E72: Confiança | F72: Riscos Geopolíticos e Estratégicos | G72: Gestão do Capital Humano | H72: Moderado | I72: Gestão ESG e Sustentabilidade | J72: Metas de diversidade na liderança estão vinculadas ao custo do sustainability-linked bond, o que dá efeito financeiro ao tema. | K72: Relatório aponta meta de mulheres na liderança abaixo do compromisso público assumido na emissão. | L72: Exemplo típico (premissa Peers)
A73: 72 | B73: 4. Responsabilidade Social | C73: Pessoas | D73: Segurança, condições e relações de trabalho | E73: Confiança | F73: Riscos Operacionais | G73: Saúde e Segurança | H73: Alto | I73: Gestão do Capital Humano | J73: Condição de trabalho e jornada. Núcleo do risco de saúde e segurança. | K73: Sindicato denuncia condições de trabalho e jornada em frente de obra da concessionária. | L73: Exemplo típico (premissa Peers)
A74: 73 | B74: 4. Responsabilidade Social | C74: Pessoas | D74: Cultura organizacional | F74: Riscos Geopolíticos e Estratégicos | G74: Gestão do Capital Humano | H74: Moderado | J74: Clima e cultura. Afeta atração e exposição em plataforma de avaliação de empregador. | K74: Relatos de clima organizacional em plataforma de avaliação de empresas viram pauta em veículo de negócios. | L74: Exemplo típico (premissa Peers)
A75: 74 | B75: 4. Responsabilidade Social | C75: Saúde e segurança | D75: Segurança dos trabalhadores / Acidentes de trabalho | F75: Riscos Operacionais | G75: Saúde e Segurança | H75: Alto | I75: Gestão de Contratos e Terceiros | J75: Acidente com empregado próprio ou de terceiro, com possível responsabilidade solidária. | K75: Acidente fatal com trabalhador terceirizado em obra de rede é noticiado e gera interdição do Ministério do Trabalho. | L75: Exemplo típico (premissa Peers)
A76: 75 | B76: 4. Responsabilidade Social | C76: Relações de trabalho | D76: Relações sindicais | F76: Riscos Geopolíticos e Estratégicos | G76: Gestão do Capital Humano | H76: Moderado | I76: Entrega de água e tratamento de esgoto | J76: Paralisação sindical pode interromper a entrega do serviço, o que conecta ao cluster Crítico. | K76: Greve de trabalhadores ameaça a continuidade do abastecimento em município atendido. | L76: Exemplo típico (premissa Peers)
A77: 76 | B77: 4. Responsabilidade Social | C77: Relações de trabalho | D77: Relacionamento com terceiros | F77: Riscos em Investimentos de Capital | G77: Gestão de Contratos e Terceiros | H77: Moderado | I77: Saúde e Segurança | J77: Gestão da cadeia de terceiros, inclusive responsabilidade solidária trabalhista. | K77: Empresa terceirizada deixa de pagar salários e a concessionária é acionada por responsabilidade solidária. | L77: Exemplo típico (premissa Peers)
A78: 77 | B78: 5. Responsabilidade Ambiental | C78: Proteção ambiental | D78: Proteção de mananciais / Recuperação ambiental | E78: Confiança | F78: Riscos Operacionais | G78: Meio ambiente operacional | H78: Alto | I78: Gestão ESG e Sustentabilidade | J78: Proteção de manancial é condição de operação e de manutenção da licença. | K78: Ocupação irregular em área de manancial usado na captação é noticiada e a concessionária é cobrada por omissão. | L78: Exemplo típico (premissa Peers)
A79: 78 | B79: 5. Responsabilidade Ambiental | C79: Proteção ambiental | D79: Oceanos | E79: Confiança | F79: Riscos Operacionais | G79: Meio ambiente operacional | H79: Alto | I79: Relações com as Comunidades | J79: Emissário submarino e qualidade da água costeira, com forte apelo público. | K79: Emissário submarino é apontado por entidade ambiental como fonte de poluição costeira. | L79: Exemplo típico (premissa Peers)
A80: 79 | B80: 5. Responsabilidade Ambiental | C80: Meio ambiente e clima | D80: Resiliência hídrica e novas fontes | E80: Confiança | F80: Riscos ESG | G80: Externalidades e Mudanças Climáticas | H80: Critico | I80: Entrega de água e tratamento de esgoto | J80: Disponibilidade hídrica sob estresse climático é causa direta do risco Crítico de entrega. | K80: Estiagem reduz o nível do manancial e a concessionária anuncia rodízio no abastecimento. | L80: Exemplo típico (premissa Peers)
A81: 80 | B81: 5. Responsabilidade Ambiental | C81: Energia | D81: Eficiência energética / Energia renovável / Autoprodução e geração distribuída | E81: Confiança | F81: Riscos Operacionais | G81: Gestão de Insumos | H81: Moderado | I81: Gestão ESG e Sustentabilidade | J81: Energia é o principal insumo de custo da operação de saneamento. | K81: Aumento do custo de energia é citado como pressão sobre a operação e como argumento em pleito tarifário. | L81: Exemplo típico (premissa Peers)
A82: 81 | B82: 5. Responsabilidade Ambiental | C82: Mudanças climáticas | D82: Emissão gases efeito estufa | E82: Confiança | F82: Riscos ESG | G82: Gestão ESG e Sustentabilidade | H82: Alto | I82: Externalidades e Mudanças Climáticas | J82: Pegada própria e metas de neutralidade, com risco de alegação sem lastro. | K82: Relatório aponta divergência entre a meta de neutralidade divulgada e a emissão efetivamente reportada. | L82: Exemplo típico (premissa Peers)
A83: 82 | B83: 5. Responsabilidade Ambiental | C83: Mudanças climáticas | D83: Eventos Climáticos | F83: Riscos ESG | G83: Externalidades e Mudanças Climáticas | H83: Critico | I83: Integridade e Confiabilidade dos Ativos | J83: Seca, enchente e evento extremo atingindo diretamente a operação. | K83: Enchente danifica estação de tratamento e interrompe o abastecimento por vários dias. | L83: Exemplo típico (premissa Peers)
A84: 83 | B84: 5. Responsabilidade Ambiental | C84: Mudanças climáticas | D84: Adaptação e resiliência | F84: Riscos ESG | G84: Externalidades e Mudanças Climáticas | H84: Critico | I84: Gestão ESG e Sustentabilidade | J84: Capacidade de adaptação da infraestrutura ao cenário climático projetado. | K84: Especialistas afirmam em reportagem que a infraestrutura não está preparada para evento extremo recorrente. | L84: Exemplo típico (premissa Peers)
A85: 84 | B85: 5. Responsabilidade Ambiental | C85: Proteção ambiental | D85: Biodiversidade | F85: Riscos em Investimentos de Capital | G85: Gestão Ambiental em Projetos e Obras | H85: Alto | I85: Meio ambiente operacional | J85: Impacto em ecossistema decorre majoritariamente de obra e de condicionante de licença. | K85: Supressão de vegetação para obra de rede gera questionamento de órgão ambiental e de entidade local. | L85: Exemplo típico (premissa Peers)
A86: 85 | B86: 5. Responsabilidade Ambiental | C86: Licenciamento ambiental | D86: Licenças e autorizações / Condicionantes ambientais / Fiscalização e autuações | F86: Riscos Operacionais | G86: Gestão de Licenças | H86: Alto | I86: Meio ambiente operacional | J86: Cluster próprio na matriz. Licença vencida ou condicionante descumprida paralisa obra e operação. | K86: Licenciamento do emissário do Rio Tramandaí, único caso de licenciamento efetivo entre os títulos rotulados como licença ambiental em janeiro. | L86: Base jan/2026 (Clipei)
A87: 86 | B87: 5. Responsabilidade Ambiental | C87: Economia circular e reúso | D87: Aproveitamento de subprodutos | F87: Riscos com Stakeholders e novos negócios | G87: Novas Tendências e Futuro | H87: Moderado | I87: Gestão ESG e Sustentabilidade | J87: Linha emergente de valorização de subproduto, ainda em estágio de anúncio. | K87: Projeto de biometano a partir de estação de tratamento é anunciado e depois cobrado por atraso. | L87: Exemplo típico (premissa Peers)
A88: 87 | B88: 5. Responsabilidade Ambiental | C88: Economia circular e reúso | D88: Gestão de lodo | F88: Riscos Operacionais | G88: Meio ambiente operacional | H88: Alto | I88: Tratamento de resíduos sólidos urbanos (RSU) | J88: Destinação de lodo é passivo ambiental recorrente da operação de estação de tratamento. | K88: Destinação irregular de lodo de estação de tratamento é autuada pelo órgão ambiental. | L88: Exemplo típico (premissa Peers)
A89: 88 | B89: 5. Responsabilidade Ambiental | C89: Economia circular e reúso | D89: Redução e valorização de resíduos | F89: Riscos ESG | G89: Gestão ESG e Sustentabilidade | H89: Alto | I89: Tratamento de resíduos sólidos urbanos (RSU) | J89: Agenda de economia circular, com compromisso público sujeito a cobrança. | K89: Compromisso público de economia circular é cobrado por entidade ambiental sem evidência de avanço. | L89: Exemplo típico (premissa Peers)
A90: 89 | B90: 6. Inovação e Tecnologia | C90: Tecnologia operação | D90: Monitoramento em tempo real | E90: Credibilidade | F90: Riscos em Investimentos de Capital | G90: Adoção e Efetividade de Novas Tecnologias | H90: Alto | I90: Integridade e Confiabilidade dos Ativos | J90: Tecnologia de monitoramento aplicada à operação. O risco é de adoção e efetividade. | K90: Falha no sistema de monitoramento retarda a identificação de vazamento de grande porte. | L90: Exemplo típico (premissa Peers)
A91: 90 | B91: 6. Inovação e Tecnologia | C91: Tecnologia operação | D91: Gestão de ativos | E91: Credibilidade | F91: Riscos Operacionais | G91: Integridade e Confiabilidade dos Ativos | H91: Alto | I91: Adoção e Efetividade de Novas Tecnologias | J91: Gestão do ciclo de vida do ativo. Núcleo do risco de confiabilidade. | K91: Reportagem aponta rede antiga sem plano de substituição em município com rompimentos recorrentes. | L91: Exemplo típico (premissa Peers)
A92: 91 | B92: 6. Inovação e Tecnologia | C92: Tecnologia operação | D92: Sensoriamento e telemetria | E92: Credibilidade | F92: Riscos em Investimentos de Capital | G92: Adoção e Efetividade de Novas Tecnologias | H92: Alto | I92: Integridade e Confiabilidade dos Ativos | J92: Instrumentação de rede, cuja falha aparece como ineficiência operacional. | K92: Investimento em telemetria é anunciado após críticas ao índice de perdas, sem prazo definido. | L92: Exemplo típico (premissa Peers)
A93: 92 | B93: 6. Inovação e Tecnologia | C93: Automação e inteligência artificial | D93: Automação de processos | E93: Credibilidade | F93: Riscos em Investimentos de Capital | G93: Adoção e Efetividade de Novas Tecnologias | H93: Alto | J93: Adoção e efetividade de automação. | K93: Falha em sistema automatizado de dosagem de produto químico é apontada em episódio de qualidade da água. | L93: Exemplo típico (premissa Peers)
A94: 93 | B94: 6. Inovação e Tecnologia | C94: Automação e inteligência artificial | D94: Inteligência artificial / Eficiência baseada em dados / Análise preditiva | E94: Credibilidade | F94: Riscos em Investimentos de Capital | G94: Adoção e Efetividade de Novas Tecnologias | H94: Alto | I94: Novas Tendências e Futuro | J94: Adoção de IA, com risco de promessa não entregue e de uso questionado. | K94: Anúncio de uso de inteligência artificial para prever vazamentos é cobrado por falta de resultado mensurável. | L94: Exemplo típico (premissa Peers)
A95: 94 | B95: 6. Inovação e Tecnologia | C95: Experiência digital do cliente | D95: Canais digitais / Autoatendimento | E95: Credibilidade | F95: Riscos com Clientes | G95: Regularidade, Atendimento e Satisfação | H95: Alto | I95: Adoção e Efetividade de Novas Tecnologias | J95: Canal digital é atendimento antes de ser tecnologia. Indisponibilidade vira reclamação de cliente. | K95: Aplicativo e site ficam fora do ar durante episódio de falta de água, com reclamação em redes sociais. | L95: Exemplo típico (premissa Peers)
A96: 95 | B96: 6. Inovação e Tecnologia | C96: Experiência digital do cliente | D96: Medição e fatura digital | E96: Credibilidade | F96: Riscos em Investimentos de Capital | G96: Adoção e Efetividade de Novas Tecnologias | H96: Alto | I96: Regularidade, Atendimento e Satisfação | J96: Telemetria de consumo e fatura digital. Falha de leitura remota recai sobre o cliente. | K96: Erro em leitura remota gera cobrança indevida a um conjunto de clientes e obriga reemissão de faturas. | L96: Exemplo típico (premissa Peers)
A97: 96 | B97: 6. Inovação e Tecnologia | C97: Pesquisa e desenvolvimento | D97: Novas tecnologias | E97: Credibilidade | F97: Riscos com Stakeholders e novos negócios | G97: Novas Tendências e Futuro | H97: Moderado | I97: Adoção e Efetividade de Novas Tecnologias | J97: Agenda de inovação e posicionamento de futuro. | K97: Projeto piloto de nova tecnologia de tratamento é anunciado em feira do setor. | L97: Exemplo típico (premissa Peers)
A98: 97 | B98: 6. Inovação e Tecnologia | C98: Pesquisa e desenvolvimento | D98: Parcerias com universidades e startups | E98: Credibilidade | F98: Riscos com Stakeholders e novos negócios | G98: Novas Tendências e Futuro | H98: Moderado | J98: Ecossistema de inovação, com exposição baixa e majoritariamente positiva. | K98: Parceria com universidade para pesquisa em perdas é anunciada e depois cobrada por resultado. | L98: Exemplo típico (premissa Peers)
A99: 98 | B99: 6. Inovação e Tecnologia | C99: Segurança da informação | D99: Proteção de dados / Privacidade / Cybersegurança / Continuidade | E99: Credibilidade | F99: Riscos de Tecnologia | G99: Cybersecurity e Continuidade Operacional | H99: Critico | I99: Proteção de Dados e informações / Proteção de Dados – LGPD | J99: Subtema único atendendo três riscos distintos, sendo um deles Crítico. Recomendação de desdobramento antes do sign-off, na aba Pontos de atenção. | K99: Vazamento de dados cadastrais de clientes é noticiado e a ANPD é acionada. | L99: Exemplo típico (premissa Peers)
A100: 99 | B100: 7. Prosperidade Compartilhada | C100: Universalização | D100: Universalização e metas de cobertura | F100: Riscos Geopolíticos e Estratégicos | G100: Legal e Regulatório | H100: Moderado | I100: Entrega de água e tratamento de esgoto | J100: Meta de universalização é obrigação contratual e regulatória antes de ser promessa institucional. | K100: Relatório aponta município fora da trajetória da meta de universalização prevista para 2033. | L100: Exemplo típico (premissa Peers)
...

Sheet Taxonomia de temas
A1: Nível 1: Pilar reputacional | B1: Nível 2: Tema estratégico | C1: Nível 3: Subtema | D1: LSO | E1: Risk tracking | F1: Issue RepRisk correspondente | G1: Detalhamento | H1: Pauta | I1: Campo de classificação da empresa | J1: To do Comunicação
A2: 1. Governança | B2: Governança corporativa | C2: Estrutura de governança / Conselho e comitês | D2: Credibilidade | E2: Sem enquadramento | H2: Espontânea | I2: Concorrentes | J2: Definição de porta-vozes
A3: 1. Governança | B3: Governança corporativa | C3: Acionistas | D3: Credibilidade | E3: Gestão de Portfólio e Estrutura de Capital | H3: Produzida | I3: Unidades Aegea | J3: Preenchimento planilha
A4: 1. Governança | B4: Contratos e Regulação | C4: Cumprimento contratual | D4: Legitimidade | E4: Legal e Regulatório | H4: Provocada | J4: Validar taxonomia
A5: 1. Governança | B5: Contratos e Regulação | C5: Revisão e renovação de contratos | D5: Legitimidade | E5: Legal e Regulatório | H5: Publicidade | J5: Usuários
A6: 1. Governança | B6: Contratos e Regulação | C6: Reequilíbrio econômico-financeiro | D6: Legitimidade | E6: Legal e Regulatório | J6: Reprisk
A7: 1. Governança | B7: Contratos e Regulação | C7: Segurança jurídica | D7: Legitimidade | E7: Legal e Regulatório | J7: Porta vozes
A8: 1. Governança | B8: Contratos e Regulação | C8: Fiscalização regulatória | D8: Legitimidade | E8: Legal e Regulatório
A9: 1. Governança | B9: Contratos e Regulação | C9: Multa e processos | D9: Credibilidade | E9: Contingências e Provisões
A10: 1. Governança | B10: Integridade | C10: Ética e conduta | D10: Credibilidade | E10: Práticas Ilegais ou Antiéticas
A11: 1. Governança | B11: Integridade | C11: Investigações e Acordo | D11: Credibilidade | E11: Práticas Ilegais ou Antiéticas
A12: 1. Governança | B12: Integridade | C12: Controles internos / Prevenção à fraude e corrupção | D12: Credibilidade | E12: Práticas Ilegais ou Antiéticas
A13: 1. Governança | B13: Integridade | C13: Demonstrações de resultados e auditoria | D13: Credibilidade | E13: Integridade das Demonstrações Financeiras
A14: 1. Governança | B14: Modelo de negócio | C14: Modelo Operacional Aegea | D14: Credibilidade | E14: Sem enquadramento
A15: 1. Governança | B15: Político-institucional | C15: Políticas públicas e setoriais | D15: Credibilidade | E15: Instabilidade Política / Econômica
A16: 1. Governança | B16: Político-institucional | C16: Patrocínios institucionais | D16: Credibilidade | E16: Relações Institucionais e Governamentais
A17: 1. Governança | B17: Político-institucional | C17: Debate público versus privado | D17: Credibilidade | E17: Instabilidade Política / Econômica
A18: 1. Governança | B18: Político-institucional | C18: Judicialização e CPIs | D18: Credibilidade | E18: Legal e Regulatório
A19: 1. Governança | B19: Político-institucional | C19: Marco Legal do Saneamento | E19: Instabilidade Política / Econômica
A20: 1. Governança | B20: Contratos e Regulação | C20: Agências reguladoras | E20: Relações Institucionais e Governamentais
A21: 1. Governança | B21: Político-institucional | C21: Agenda Associações (Políticas setoriais) | D21: Credibilidade | E21: Relações Institucionais e Governamentais
A22: 2. Eficiência Operacional e Qualidade | B22: Abastecimento de água | C22: Frequência, Continuidade | D22: Legitimidade | E22: Entrega de água e tratamento de esgoto
A23: 2. Eficiência Operacional e Qualidade | B23: Abastecimento de água | C23: Perdas, fraudes, furtos e ligações irregulares | D23: Legitimidade | E23: Integridade e Confiabilidade dos Ativos
A24: 2. Eficiência Operacional e Qualidade | B24: Abastecimento de água | C24: Rompimento de adutora | D24: Legitimidade | E24: Integridade e Confiabilidade dos Ativos
A25: 2. Eficiência Operacional e Qualidade | B25: Abastecimento de água | C25: Plano de contingência e redundância | D25: Legitimidade | E25: Gestão de Crises
A26: 2. Eficiência Operacional e Qualidade | B26: Qualidade da água | C26: Gestão da qualidade da água | D26: Legitimidade | E26: Entrega de água e tratamento de esgoto
A27: 2. Eficiência Operacional e Qualidade | B27: Qualidade da água | C27: Monitoramento e controle de qualidade da água | D27: Legitimidade | E27: Entrega de água e tratamento de esgoto
A28: 2. Eficiência Operacional e Qualidade | B28: Qualidade da água | C28: Potabilidade | D28: Legitimidade | E28: Entrega de água e tratamento de esgoto
A29: 2. Eficiência Operacional e Qualidade | B29: Esgoto | C29: Rede e Coleta de esgoto | D29: Legitimidade | E29: Entrega de água e tratamento de esgoto
A30: 2. Eficiência Operacional e Qualidade | B30: Esgoto | C30: Tratamento de esgoto | D30: Legitimidade | E30: Entrega de água e tratamento de esgoto
A31: 2. Eficiência Operacional e Qualidade | B31: Esgoto | C31: Lançamento irregular e extravasamento | D31: Legitimidade | E31: Meio ambiente operacional
A32: 2. Eficiência Operacional e Qualidade | B32: Esgoto | C32: Balneabilidade | D32: Legitimidade | E32: Meio ambiente operacional
A33: 2. Eficiência Operacional e Qualidade | B33: Esgoto | C33: Odor e incômodo | E33: Relações com as Comunidades
A34: 2. Eficiência Operacional e Qualidade | B34: Obras e intervenções | C34: Custos e eficiência | D34: Credibilidade | E34: Gestão de Contratos e Terceiros
A35: 2. Eficiência Operacional e Qualidade | B35: Obras e intervenções | C35: Acidentes e danos a terceiros | D35: Credibilidade | E35: Saúde e Segurança
A36: 2. Eficiência Operacional e Qualidade | B36: Obras e intervenções | C36: Expansão da rede | D36: Credibilidade | E36: Gestão de Contratos e Terceiros
A37: 2. Eficiência Operacional e Qualidade | B37: Obras e intervenções | C37: Pavimentação e recomposição | D37: Credibilidade | E37: Gestão de Contratos e Terceiros
A38: 2. Eficiência Operacional e Qualidade | B38: Obras e intervenções | C38: Manutenção, interdições e transtornos urbanos | D38: Credibilidade | E38: Relações com as Comunidades
A39: 2. Eficiência Operacional e Qualidade | B39: Atendimento ao cliente | C39: Canais de atendimento | D39: Credibilidade | E39: Regularidade, Atendimento e Satisfação
A40: 2. Eficiência Operacional e Qualidade | B40: Atendimento ao cliente | C40: Atendimento ao cliente | D40: Credibilidade | E40: Regularidade, Atendimento e Satisfação
A41: 2. Eficiência Operacional e Qualidade | B41: Atendimento ao cliente | C41: Órgãos de defesa ao cliente (Ouvidoria, Procon, Reclame Aqui) | D41: Credibilidade | E41: Regularidade, Atendimento e Satisfação
A42: 2. Eficiência Operacional e Qualidade | B42: Faturamento e cobrança | C42: Medição e leitura | E42: Regularidade, Atendimento e Satisfação
A43: 2. Eficiência Operacional e Qualidade | B43: Faturamento e cobrança | C43: Conta errada, Tarifa abusiva | E43: Regularidade, Atendimento e Satisfação
A44: 2. Eficiência Operacional e Qualidade | B44: Faturamento e cobrança | C44: Inadimplência, Corte e religação | E44: Gestão de Crédito e Inadimplência
A45: 2. Eficiência Operacional e Qualidade | B45: Segurança operacional e patrimonial | C45: Segurança, ameaças e invasões | E45: Integridade e Confiabilidade dos Ativos
A46: 3. Crescimento e Solidez Financeira | B46: Tarifa | C46: Reajuste/ Revisão tarifária | E46: Legal e Regulatório
A47: 3. Crescimento e Solidez Financeira | B47: Tarifa | C47: Estrutura e composição tarifária | E47: Legal e Regulatório
A48: 3. Crescimento e Solidez Financeira | B48: Desempenho financeiro | C48: Resultados financeiros e operacionais | E48: Integridade das Informações ao Mercado
A49: 3. Crescimento e Solidez Financeira | B49: Desempenho financeiro | C49: Projeções e guidance | E49: Integridade das Informações ao Mercado
A50: 3. Crescimento e Solidez Financeira | B50: Estrutura de capital | C50: Endividamento e alavancagem | E50: Liquidez, Gestão da Dívida e Quebra de Covenants de financiamentos
A51: 3. Crescimento e Solidez Financeira | B51: Estrutura de capital | C51: Aportes dos acionistas | E51: Gestão de Portfólio e Estrutura de Capital
A52: 3. Crescimento e Solidez Financeira | B52: Estrutura de capital | C52: Dividendos e distribuição de capital | E52: Gestão de Portfólio e Estrutura de Capital
A53: 3. Crescimento e Solidez Financeira | B53: Estrutura de capital | C53: Emissão de dívida / Debêntures e bonds | E53: Liquidez, Gestão da Dívida e Quebra de Covenants de financiamentos
... A63: 3. Crescimento e Solidez Financeira | B63: Novos negócios | C63: Reúso de água | E63: Novas Tendências e Futuro
A64: 4. Responsabilidade Social | B64: Ações Sociais | C64: Programas sociais e comunidade | D64: Confiança | E64: Relações com as Comunidades
A65: 4. Responsabilidade Social | B65: Inclusão sanitária / Acessibilidade econômica | C65: Tarifa social | E65: Relações com as Comunidades
A66: 4. Responsabilidade Social | B66: Inclusão sanitária / Acessibilidade econômica | C66: Cadastro e elegibilidade | E66: Regularidade, Atendimento e Satisfação
A67: 4. Responsabilidade Social | B67: Inclusão sanitária / Acessibilidade econômica | C67: Renegociação e apoio ao cliente | E67: Gestão de Crédito e Inadimplência
A68: 4. Responsabilidade Social | B68: Relacionamento comunitário | C68: Prêmios, Projetos e incentivos à comunidade | E68: Relações com as Comunidades
A69: 4. Responsabilidade Social | B69: Educação e conscientização | C69: Educação ambiental / Engajamento em saneamento e saúde / Uso consciente da água | E69: Relações com as Comunidades
A70: 4. Responsabilidade Social | B70: Pessoas | C70: Contratação | D70: Confiança | E70: Gestão do Capital Humano
A71: 4. Responsabilidade Social | B71: Pessoas | C71: Atração e desenvolvimento | D71: Confiança | E71: Gestão do Capital Humano
A72: 4. Responsabilidade Social | B72: Pessoas | C72: Equidade, Diversidade e inclusão | D72: Confiança | E72: Gestão do Capital Humano
A73: 4. Responsabilidade Social | B73: Pessoas | C73: Segurança, condições e relações de trabalho | D73: Confiança | E73: Saúde e Segurança
A74: 4. Responsabilidade Social | B74: Pessoas | C74: Cultura organizacional | E74: Gestão do Capital Humano
A75: 4. Responsabilidade Social | B75: Saúde e segurança | C75: Segurança dos trabalhadores / Acidentes de trabalho | E75: Saúde e Segurança
A76: 4. Responsabilidade Social | B76: Relações de trabalho | C76: Relações sindicais | E76: Gestão do Capital Humano
A77: 4. Responsabilidade Social | B77: Relações de trabalho | C77: Relacionamento com terceiros | E77: Gestão de Contratos e Terceiros
A78: 5. Responsabilidade Ambiental | B78: Proteção ambiental | C78: Proteção de mananciais / Recuperação ambiental | D78: Confiança | E78: Meio ambiente operacional
A79: 5. Responsabilidade Ambiental | B79: Proteção ambiental | C79: Oceanos | D79: Confiança | E79: Meio ambiente operacional
A80: 5. Responsabilidade Ambiental | B80: Meio ambiente e clima | C80: Resiliência hídrica e novas fontes | D80: Confiança | E80: Externalidades e Mudanças Climáticas
A81: 5. Responsabilidade Ambiental | B81: Energia | C81: Eficiência energética / Energia renovável / Autoprodução e geração distribuída | D81: Confiança | E81: Gestão de Insumos
A82: 5. Responsabilidade Ambiental | B82: Mudanças climáticas | C82: Emissão gases efeito estufa | D82: Confiança | E82: Gestão ESG e Sustentabilidade
A83: 5. Responsabilidade Ambiental | B83: Mudanças climáticas | C83: Eventos Climáticos | E83: Externalidades e Mudanças Climáticas
A84: 5. Responsabilidade Ambiental | B84: Mudanças climáticas | C84: Adaptação e resiliência | E84: Externalidades e Mudanças Climáticas
A85: 5. Responsabilidade Ambiental | B85: Proteção ambiental | C85: Biodiversidade | E85: Gestão Ambiental em Projetos e Obras
A86: 5. Responsabilidade Ambiental | B86: Licenciamento ambiental | C86: Licenças e autorizações / Condicionantes ambientais / Fiscalização e autuações | E86: Gestão de Licenças
A87: 5. Responsabilidade Ambiental | B87: Economia circular e reúso | C87: Aproveitamento de subprodutos | E87: Novas Tendências e Futuro
A88: 5. Responsabilidade Ambiental | B88: Economia circular e reúso | C88: Gestão de lodo | E88: Meio ambiente operacional
A89: 5. Responsabilidade Ambiental | B89: Economia circular e reúso | C89: Redução e valorização de resíduos | E89: Gestão ESG e Sustentabilidade
A90: 6. Inovação e Tecnologia | B90: Tecnologia operação | C90: Monitoramento em tempo real | D90: Credibilidade | E90: Adoção e Efetividade de Novas Tecnologias
A91: 6. Inovação e Tecnologia | B91: Tecnologia operação | C91: Gestão de ativos | D91: Credibilidade | E91: Integridade e Confiabilidade dos Ativos
A92: 6. Inovação e Tecnologia | B92: Tecnologia operação | C92: Sensoriamento e telemetria | D92: Credibilidade | E92: Adoção e Efetividade de Novas Tecnologias
A93: 6. Inovação e Tecnologia | B93: Automação e inteligência artificial | C93: Automação de processos | D93: Credibilidade | E93: Adoção e Efetividade de Novas Tecnologias
A94: 6. Inovação e Tecnologia | B94: Automação e inteligência artificial | C94: Inteligência artificial / Eficiência baseada em dados / Análise preditiva | D94: Credibilidade | E94: Adoção e Efetividade de Novas Tecnologias
A95: 6. Inovação e Tecnologia | B95: Experiência digital do cliente | C95: Canais digitais / Autoatendimento | D95: Credibilidade | E95: Regularidade, Atendimento e Satisfação
A96: 6. Inovação e Tecnologia | B96: Experiência digital do cliente | C96: Medição e fatura digital | D96: Credibilidade | E96: Adoção e Efetividade de Novas Tecnologias
A97: 6. Inovação e Tecnologia | B97: Pesquisa e desenvolvimento | C97: Novas tecnologias | D97: Credibilidade | E97: Novas Tendências e Futuro
A98: 6. Inovação e Tecnologia | B98: Pesquisa e desenvolvimento | C98: Parcerias com universidades e startups | D98: Credibilidade | E98: Novas Tendências e Futuro
A99: 6. Inovação e Tecnologia | B99: Segurança da informação | C99: Proteção de dados / Privacidade / Cybersegurança / Continuidade | D99: Credibilidade | E99: Cybersecurity e Continuidade Operacional
A100: 7. Prosperidade Compartilhada | B100: Universalização | C100: Universalização e metas de cobertura | E100: Legal e Regulatório
A101: 7. Prosperidade Compartilhada | B101: Investimento em infraestrutura | C101: Volume de investimentos | E101: Gestão de Portfólio e Estrutura de Capital
A102: 7. Prosperidade Compartilhada | B102: Legado e impacto | C102: Benefícios do saneamento (saúde, educação, imóveis, socioeconômico) | E102: Sem enquadramento
A103: 7. Prosperidade Compartilhada | B103: Emprego e renda | C103: Geração de empregos / Contratação local / Capacitação profissional | E103: Relações com as Comunidades
A104: 7. Prosperidade Compartilhada | B104: Cadeia de valor | C104: Desenvolvimento de fornecedores / Fornecedores locais / Compras responsáveis | E104: Gestão de Contratos e Terceiros
A105: 7. Prosperidade Compartilhada | B105: Cadeia de valor | C105: Drenagem urbana e águas pluviais | E105: Sem enquadramento

Sheet Risk tracking map
A1: Risk Cluster | B1: Risk | C1: Severity | D1: Subtemas atribuídos (primário) | E1: Subtemas atribuídos (secundário)
A2: Riscos Geopolíticos e Estratégicos | B2: Instabilidade Política / Econômica | C2: Moderado | D2: =COUNTIF('De-para Risk tracking'!$G$2:$G$105,$B2) -> 3 | E2: =COUNTIF('De-para Risk tracking'!$I$2:$I$105,$B2) -> 3
A3: Riscos Geopolíticos e Estratégicos | B3: Relações Institucionais e Governamentais | C3: Moderado | D3: =COUNTIF('De-para Risk tracking'!$G$2:$G$105,$B3) -> 3 | E3: =COUNTIF('De-para Risk tracking'!$I$2:$I$105,$B3) -> 3
A4: Riscos Geopolíticos e Estratégicos | B4: Gestão de Portfólio e Estrutura de Capital | C4: Alto | D4: =COUNTIF('De-para Risk tracking'!$G$2:$G$105,$B4) -> 6 | E4: =COUNTIF('De-para Risk tracking'!$I$2:$I$105,$B4) -> 4
A5: Riscos Geopolíticos e Estratégicos | B5: Liquidez, Gestão da Dívida e Quebra de Covenants de financiamentos | C5: Alto | D5: =COUNTIF('De-para Risk tracking'!$G$2:$G$105,$B5) -> 4 | E5: =COUNTIF('De-para Risk tracking'!$I$2:$I$105,$B5) -> 3
A6: Riscos Geopolíticos e Estratégicos | B6: Legal e Regulatório | C6: Moderado | D6: =COUNTIF('De-para Risk tracking'!$G$2:$G$105,$B6) -> 9 | E6: =COUNTIF('De-para Risk tracking'!$I$2:$I$105,$B6) -> 5
A7: Riscos Geopolíticos e Estratégicos | B7: Práticas Ilegais ou Antiéticas | C7: Alto | D7: =COUNTIF('De-para Risk tracking'!$G$2:$G$105,$B7) -> 3 | E7: =COUNTIF('De-para Risk tracking'!$I$2:$I$105,$B7) -> 3
A8: Riscos Geopolíticos e Estratégicos | B8: Gestão do Capital Humano | C8: Moderado | D8: =COUNTIF('De-para Risk tracking'!$G$2:$G$105,$B8) -> 5 | E8: =COUNTIF('De-para Risk tracking'!$I$2:$I$105,$B8) -> 2
A9: Riscos em Investimentos de Capital | B9: Gestão de Contratos e Terceiros | C9: Moderado | D9: =COUNTIF('De-para Risk tracking'!$G$2:$G$105,$B9) -> 5 | E9: =COUNTIF('De-para Risk tracking'!$I$2:$I$105,$B9) -> 5
A10: Riscos em Investimentos de Capital | B10: Adoção e Efetividade de Novas Tecnologias | C10: Alto | D10: =COUNTIF('De-para Risk tracking'!$G$2:$G$105,$B10) -> 5 | E10: =COUNTIF('De-para Risk tracking'!$I$2:$I$105,$B10) -> 3
A11: Riscos em Investimentos de Capital | B11: Gestão Ambiental em Projetos e Obras | C11: Alto | D11: =COUNTIF('De-para Risk tracking'!$G$2:$G$105,$B11) -> 1 | E11: =COUNTIF('De-para Risk tracking'!$I$2:$I$105,$B11) -> 1
A12: Riscos Operacionais | B12: Gestão de Insumos | C12: Moderado | D12: =COUNTIF('De-para Risk tracking'!$G$2:$G$105,$B12) -> 1 | E12: =COUNTIF('De-para Risk tracking'!$I$2:$I$105,$B12) -> 0
A13: Riscos Operacionais | B13: Gestão de Licenças | C13: Alto | D13: =COUNTIF('De-para Risk tracking'!$G$2:$G$105,$B13) -> 1 | E13: =COUNTIF('De-para Risk tracking'!$I$2:$I$105,$B13) -> 2
... A33: Riscos com Stakeholders e novos negócios | B33: Novas Tendências e Futuro | C33: Moderado | D33: =COUNTIF('De-para Risk tracking'!$G$2:$G$105,$B33) -> 4 | E33: =COUNTIF('De-para Risk tracking'!$I$2:$I$105,$B33) -> 1

Sheet Pontos de atenção
A1: # | B1: Tipo | C1: Ponto | D1: Evidência | E1: Criticidade | F1: Recomendação
A2: 1 | B2: Taxonomia | C2: Segurança da informação é um subtema para três riscos | D2: Cybersecurity é Crítico, Proteção de Dados é Alto e LGPD é Moderado. A taxonomia funde os três em um subtema só. | E2: Alta | F2: Desdobrar em três subtemas antes do sign-off. Enquanto estiver fundido, o painel não separa o risco Crítico do Moderado, e Proteção de Dados e LGPD ficam com zero subtema primário.
A3: 2 | B3: Método | C3: Gestão de Crises recebe um único subtema | D3: Risco Crítico atendido apenas por Plano de contingência e redundância. Crise atravessa os outros 31 riscos. | E3: Alta | F3: Tratar crise como atributo do evento, não como destino de subtema. Caso contrário o risco mais severo fica subdimensionado no painel.
A4: 3 | B4: Concentração | C4: Legal e Regulatório concentra o maior número de subtemas e é Moderado | D4: Nove subtemas apontam para um risco de severidade média. É a maior concentração da taxonomia. | E4: Alta | F4: Checar com Riscos. Ou a taxonomia superdimensiona o eixo regulatório, ou a matriz subdimensiona o risco. O painel vai gerar alerta de volume alto num risco de segunda ordem.
A5: 4 | B5: Lacuna | C5: Integridade estrutural de ativo crítico | D5: Integridade e Confiabilidade dos Ativos é Alto e não tem subtema cobrindo integridade de barragem ou reservatório. | E5: Alta | F5: Criar subtema sob Eficiência Operacional, conectado a Eventos Climáticos.
A6: 5 | B6: Lacuna | C6: Produtos químicos de tratamento | D6: Gestão de Insumos ficou com um único subtema, energia. O insumo de maior criticidade operacional do setor não existe na taxonomia. | E6: Média | F6: Criar subtema de insumos de tratamento sob Eficiência Operacional.
A7: 6 | B7: Lacuna | C7: Conduta concorrencial | D7: Nenhum subtema dedicado. O ponto mais próximo é Novos Negócios e Leilões. | E7: Alta | F7: Criar subtema sob Integridade ou ampliar o escopo de Novos Negócios e Leilões.
A8: 7 | B8: Cobertura | C8: Cobertura de Seguros fica sem nenhum subtema | D8: Risco Moderado sem expressão pública, salvo em sinistro de grande porte. | E8: Baixa | F8: Registrar a ausência como decisão consciente, para não parecer falha de mapeamento.
A9: 8 | B9: Escopo | C9: Drenagem urbana sem dono na matriz | D9: Fora do escopo contratual na maior parte das concessões, mas o alagamento é atribuído à Aegea. | E9: Média | F9: Tratar como risco de atribuição indevida, com resposta preparada. Não forçar enquadramento.
A10: 9 | B10: Dado | C10: Exemplos de notícia sem lastro completo na base | D10: Cinco linhas têm exemplo observado na base de janeiro. As demais usam formulação típica, porque a base não está reclassificada nos 104 subtemas. | E10: Média | F10: Reclassificar a amostra de janeiro nos 104 subtemas e substituir os exemplos típicos por títulos reais antes de publicar o material.
A11: 10 | B11: Validação | C11: Atribuição não validada com a área de Riscos | D11: As 104 linhas são premissa Peers. A severidade é do cliente, a atribuição não. | E11: Alta | F11: Rodar a validação com Riscos antes do sign-off. Colunas M e N da aba De-para.
